README.rst
setup.py
gdo/__init__.py
gdo/_display.py
gdo/_sync.py
gdo/errors.py
gdo.egg-info/PKG-INFO
gdo.egg-info/SOURCES.txt
gdo.egg-info/dependency_links.txt
gdo.egg-info/requires.txt
gdo.egg-info/top_level.txt