Metadata-Version: 1.0
Name: gdo
Version: 0.1.2
Summary: Concurrent execution library
Home-page: https://github.com/uluyol/gdo
Author: Muhammed Uluyol
Author-email: uluyol0@gmail.com
License: MIT
Platform: UNKNOWN
